Metadata-Version: 1.0
Name: jz-distributions
Version: 0.1
Summary: Gaussian distribution and binomial distribution
Home-page: UNKNOWN
Author: UNKNOWN
Author-email: UNKNOWN
License: UNKNOWN
Platform: UNKNOWN
